RevImg/RevImg.py
RevImg/__init__.py
RevImg-0.0.1.dist-info/LICENSE
RevImg-0.0.1.dist-info/METADATA
RevImg-0.0.1.dist-info/WHEEL
RevImg-0.0.1.dist-info/top_level.txt
RevImg-0.0.1.dist-info/RECORD
