Metadata-Version: 2.1
Name: RevImg
Version: 0.0.1
Summary: A package to interact with the google reverse image search service
Home-page: https://github.com/infobiac/RevImg
Author: Christophe Rimann
Author-email: infobiac1@gmail.com
License: UNKNOWN
Platform: UNKNOWN
Classifier: Programming Language :: Python :: 3
Classifier: License :: OSI Approved :: MIT License
Classifier: Operating System :: OS Independent
